logdog/__init__.py
logdog/exceptions.py
logdog/_util/__init__.py
logdog/_util/duration.py
logdog/encoder/__init__.py
logdog/encoder/base_encoder.py
logdog/encoder/json_encoder.py
logdog/encoder/logfmt_encoder.py
logdog/formatter/__init__.py
logdog/formatter/base_formatter.py
logdog/formatter/common.py
logdog/formatter/json_formatter.py
logdog/formatter/logfmt_formatter.py
logdog/handler/__init__.py
logdog/handler/base_buffered_handler.py
logdog/handler/buffered_google_chat_handler.py
logdog/handler/buffered_smtp_handler.py
logdog/handler/google_chat_handler.py
logdog/wrapper/__init__.py
logdog/wrapper/log_extra_wrapper.py
logdog/wrapper/log_message_wrapper.py
python_logdog-0.4.0.dist-info/LICENSE
python_logdog-0.4.0.dist-info/METADATA
python_logdog-0.4.0.dist-info/WHEEL
python_logdog-0.4.0.dist-info/top_level.txt
python_logdog-0.4.0.dist-info/RECORD
