Metadata-Version: 2.1
Name: python-logdog
Version: 0.4.0
Summary: Python logging utilities
Author: Adam Wasilewski
License: MIT License
Project-URL: Documentation, https://a-was.github.io/logdog.py/
Project-URL: Homepage, https://github.com/a-was/logdog.py
Project-URL: Repository, https://github.com/a-was/logdog.py
Keywords: logging
Classifier: Programming Language :: Python :: 3
Classifier: Intended Audience :: Developers
Classifier: Topic :: System :: Logging
Classifier: Topic :: Utilities
Classifier: Topic :: Software Development :: Libraries :: Python Modules
Classifier: Typing :: Typed
Classifier: License :: OSI Approved :: MIT License
Requires-Python: >=3.10
License-File: LICENSE
